Metadata-Version: 2.1
Name: zarr-swiftstore
Version: 1.2.3
Summary: swift storage backend for zarr
Home-page: https://github.com/siligam/zarr-swiftstore
Author: Pavan Siligam
Author-email: pavan.siligam@gmail.com
License: MIT
Platform: UNKNOWN
Classifier: Development Status :: 4 - Beta
Classifier: Intended Audience :: Developers
Classifier: Intended Audience :: Information Technology
Classifier: Intended Audience :: Science/Research
Classifier: License :: OSI Approved :: MIT License
Classifier: Programming Language :: Python :: 3
Classifier: Programming Language :: Python :: 3.6
Classifier: Programming Language :: Python :: 3.7
Classifier: Programming Language :: Python :: 3.8
Requires-Python: >=3.5
